paypayopa/__init__.py
paypayopa/client.py
paypayopa/errors.py
paypayopa/constants/__init__.py
paypayopa/constants/api_list.py
paypayopa/constants/error_code.py
paypayopa/constants/http_status_code.py
paypayopa/constants/url.py
paypayopa/resources/__init__.py
paypayopa/resources/account.py
paypayopa/resources/base.py
paypayopa/resources/cashback.py
paypayopa/resources/code.py
paypayopa/resources/payment.py
paypayopa/resources/pending.py
paypayopa/resources/preauth.py
paypayopa/resources/user.py
paypayopa-1.7.dist-info/LICENSE
paypayopa-1.7.dist-info/METADATA
paypayopa-1.7.dist-info/WHEEL
paypayopa-1.7.dist-info/top_level.txt
paypayopa-1.7.dist-info/RECORD
