Metadata-Version: 2.1
Name: paypayopa
Version: 1.7
Summary: PayPay OPA SDK
Home-page: UNKNOWN
Author: Team PayPay
Author-email: opensource@paypay-corp.co.jp
License: Apache 2.0
Project-URL: Documentation, https://github.com/paypay/paypayopa-sdk-python/README.md
Project-URL: Source, https://github.com/paypay/paypayopa-sdk-python
Keywords: paypay payment gateway japan
Platform: UNKNOWN
Classifier: Intended Audience :: Developers
Classifier: License :: OSI Approved :: Apache Software License
Classifier: Programming Language :: Python :: 3.5
Classifier: Programming Language :: Python :: 3.6
Classifier: Programming Language :: Python :: 3.7
Classifier: Programming Language :: Python :: 3.8
Classifier: Topic :: Software Development :: Libraries :: Python Modules
Provides-Extra: test
